<PAMDataset>
  <SRS dataAxisToSRSAxisMapping="2,1">GEOGCS["WGS 84",DATUM["WGS_1984",SPHEROID["WGS 84",6378137,298.257223563,AUTHORITY["EPSG","7030"]],AUTHORITY["EPSG","6326"]],PRIMEM["Greenwich",0,AUTHORITY["EPSG","8901"]],UNIT["degree",0.0174532925199433,AUTHORITY["EPSG","9122"]],AXIS["Latitude",NORTH],AXIS["Longitude",EAST],AUTHORITY["EPSG","4326"]]</SRS>
  <Metadata domain="IMAGE_STRUCTURE">
    <MDI key="INTERLEAVE">PIXEL</MDI>
  </Metadata>
  <Metadata>
    <MDI key="DataType">Generic</MDI>
  </Metadata>
  <Metadata domain="Esri">
    <MDI key="PyramidResamplingType">NEAREST</MDI>
  </Metadata>
  <PAMRasterBand band="1">
    <Histograms>
      <HistItem>
        <HistMin>-0.5</HistMin>
        <HistMax>255.5</HistMax>
        <BucketCount>256</BucketCount>
        <IncludeOutOfRange>1</IncludeOutOfRange>
        <Approximate>0</Approximate>
        <HistCounts>29311364|0|0|0|0|109845|0|0|0|0|0|0|0|0|0|0|0|0|0|0|1037|0|0|0|0|0|0|0|0|0|0|0|0|0|1083|0|0|0|0|0|0|0|0|0|0|0|0|0|1110|0|0|0|0|0|0|0|0|0|0|1067|0|0|0|0|0|0|0|0|0|1062|0|0|0|0|0|0|0|1090|0|0|0|0|0|0|1042|0|0|0|0|0|0|1130|0|0|0|0|1155|0|0|0|0|1094|0|0|0|0|1189|0|0|0|1125|0|0|1088|0|0|0|1163|0|0|1229|0|0|1217|0|0|1207|0|0|1196|0|1277|0|0|1218|0|1193|0|0|1271|0|1195|0|1209|0|1285|0|1223|0|0|1287|0|1254|0|1268|1353|0|1267|0|1346|0|1327|0|1424|0|1334|1394|0|1477|0|1299|1450|0|1505|1446|0|1521|1483|0|1570|1438|0|1498|1523|0|1502|1570|0|1562|1487|1602|0|1642|1756|1647|0|1820|1713|1740|1737|0|1791|1744|1767|1777|0|1872|1832|1864|1789|1856|1831|1886|0|1936|1934|1909|1931|1909|1992|2027|2101|2180|1946|1967|2034|2172|2155|2130|2032|2114|2122|2131|2230|2202|2170|2183|2197|2145|2332|2161|2220|2256|4496|2331|2401|2326|2427|2374|2426|4829|2539|2515|2415|2522|389966</HistCounts>
      </HistItem>
    </Histograms>
    <Metadata>
      <MDI key="SourceBandIndex">0</MDI>
      <MDI key="STATISTICS_COUNT">30005000.000000</MDI>
      <MDI key="STATISTICS_COVARIANCES">1092.362408365178,667.8022090380994,161.9760324811325,1148.437457183666</MDI>
      <MDI key="STATISTICS_EXCLUDEDVALUES"></MDI>
      <MDI key="STATISTICS_MAXIMUM">255</MDI>
      <MDI key="STATISTICS_MEAN">4.6108587568745</MDI>
      <MDI key="STATISTICS_MEDIAN">0.000000</MDI>
      <MDI key="STATISTICS_MINIMUM">0</MDI>
      <MDI key="STATISTICS_SKIPFACTORX">1</MDI>
      <MDI key="STATISTICS_SKIPFACTORY">1</MDI>
      <MDI key="STATISTICS_STDDEV">33.05090631685</MDI>
    </Metadata>
  </PAMRasterBand>
  <PAMRasterBand band="2">
    <Histograms>
      <HistItem>
        <HistMin>-0.5</HistMin>
        <HistMax>255.5</HistMax>
        <BucketCount>256</BucketCount>
        <IncludeOutOfRange>1</IncludeOutOfRange>
        <Approximate>0</Approximate>
        <HistCounts>29601005|0|1399|0|0|0|0|0|1395|0|0|0|0|0|0|1338|0|0|0|0|0|1330|0|0|0|0|0|0|1452|0|0|0|0|0|0|1400|0|0|0|0|0|1356|0|0|0|0|0|1373|0|0|0|0|0|1372|0|0|0|0|1327|0|0|0|1385|0|0|0|0|1363|0|0|0|1389|0|0|0|1331|0|0|0|1278|0|0|1341|0|0|1361|0|0|1402|0|0|1317|0|1323|0|0|1311|0|1335|0|0|1388|0|1349|0|1378|0|1274|1238|0|1350|0|1278|0|1310|1276|0|1311|1211|0|1251|1239|0|1268|1324|1250|0|1324|1241|1241|1296|1285|0|1290|1259|1219|1323|1242|1198|1254|1213|1330|1278|1206|1214|1242|1170|1167|1192|1232|1173|1266|1156|1055|1214|1219|2342|1183|1124|1164|1186|1137|2260|1171|1110|1113|2315|1154|1076|2299|1076|1059|2186|1066|1063|2244|1105|2122|1080|2155|1038|1072|2150|1038|2016|2131|998|2027|1052|2005|988|2007|1972|1051|1981|1973|996|1998|2013|941|1834|1981|1836|1922|943|1805|1779|1880|1767|1756|852|1742|1727|1768|1768|1728|1730|2014|2955|3055|2988|3050|3054|4427|2737|2870|2777|2836|2733|2680|4033|2680|2655|2486|3814|2532|2528|3770|2404|2373|3618|2341|2369|3505|2268|3456|2223|3416|2098|3409|2100|3364|2207|3259|3189|112595</HistCounts>
      </HistItem>
    </Histograms>
    <Metadata>
      <MDI key="SourceBandIndex">1</MDI>
      <MDI key="STATISTICS_COUNT">30005000.000000</MDI>
      <MDI key="STATISTICS_COVARIANCES">667.8022090380994,589.7120030597406,171.5809567622394,677.2963791878365</MDI>
      <MDI key="STATISTICS_EXCLUDEDVALUES"></MDI>
      <MDI key="STATISTICS_MAXIMUM">255</MDI>
      <MDI key="STATISTICS_MEAN">2.7192755874015</MDI>
      <MDI key="STATISTICS_MEDIAN">0.000000</MDI>
      <MDI key="STATISTICS_MINIMUM">0</MDI>
      <MDI key="STATISTICS_SKIPFACTORX">1</MDI>
      <MDI key="STATISTICS_SKIPFACTORY">1</MDI>
      <MDI key="STATISTICS_STDDEV">24.28398655616</MDI>
    </Metadata>
  </PAMRasterBand>
  <PAMRasterBand band="3">
    <Histograms>
      <HistItem>
        <HistMin>-0.5</HistMin>
        <HistMax>255.5</HistMax>
        <BucketCount>256</BucketCount>
        <IncludeOutOfRange>1</IncludeOutOfRange>
        <Approximate>0</Approximate>
        <HistCounts>29897005|0|411|0|0|0|0|0|373|0|0|0|0|0|408|0|0|0|0|0|0|368|0|0|0|0|0|0|380|0|0|0|0|0|0|381|0|0|0|0|0|368|0|0|0|0|0|368|0|0|0|0|390|0|0|0|0|414|0|0|0|0|381|0|0|0|368|0|0|0|0|365|0|0|0|399|0|0|372|0|0|0|415|0|0|381|0|0|407|0|374|0|0|361|0|0|397|0|364|0|374|0|381|0|374|0|374|0|411|0|404|0|388|395|0|392|397|0|390|361|0|371|378|0|367|373|373|346|0|400|401|357|398|379|0|377|380|393|389|386|407|384|375|428|399|383|397|393|350|372|373|369|422|804|376|378|393|389|369|857|370|418|396|921|403|405|438|812|415|355|809|397|371|797|427|872|425|385|783|414|812|450|834|423|819|411|882|389|779|845|419|861|894|445|850|886|428|874|866|481|906|898|903|878|476|838|893|842|958|881|915|889|910|879|424|858|824|798|1186|842|795|742|772|729|726|717|732|997|685|660|741|822|1183|890|834|1210|815|919|1254|836|878|1430|899|1391|937|1438|1010|1504|1095|1671|1169|1752|1352|2068|2190|1121</HistCounts>
      </HistItem>
    </Histograms>
    <Metadata>
      <MDI key="SourceBandIndex">2</MDI>
      <MDI key="STATISTICS_COUNT">30005000.000000</MDI>
      <MDI key="STATISTICS_COVARIANCES">161.9760324811325,171.5809567622394,139.1817796285809,169.398878761726</MDI>
      <MDI key="STATISTICS_EXCLUDEDVALUES"></MDI>
      <MDI key="STATISTICS_MAXIMUM">255</MDI>
      <MDI key="STATISTICS_MEAN">0.6801191468088</MDI>
      <MDI key="STATISTICS_MEDIAN">0.000000</MDI>
      <MDI key="STATISTICS_MINIMUM">0</MDI>
      <MDI key="STATISTICS_SKIPFACTORX">1</MDI>
      <MDI key="STATISTICS_SKIPFACTORY">1</MDI>
      <MDI key="STATISTICS_STDDEV">11.797532777178</MDI>
    </Metadata>
  </PAMRasterBand>
  <PAMRasterBand band="4">
    <Histograms>
      <HistItem>
        <HistMin>-0.5</HistMin>
        <HistMax>255.5</HistMax>
        <BucketCount>256</BucketCount>
        <IncludeOutOfRange>1</IncludeOutOfRange>
        <Approximate>0</Approximate>
        <HistCounts>29307513|0|0|0|0|0|0|0|0|0|0|0|0|0|0|0|0|0|0|0|0|0|0|0|0|0|0|0|0|0|0|0|0|0|0|0|0|0|0|0|0|0|0|0|0|0|0|0|0|0|0|0|0|0|0|0|0|0|0|0|0|0|0|0|0|0|0|0|0|0|0|0|0|0|0|0|0|0|0|0|0|0|0|0|0|0|0|0|0|0|0|0|0|0|0|0|0|0|0|0|0|0|0|0|0|0|0|0|0|0|0|0|0|0|0|0|0|0|0|0|0|0|0|0|0|0|0|0|0|0|0|0|0|0|0|0|0|0|0|0|0|0|0|0|0|0|0|0|0|0|0|0|0|0|0|0|0|0|0|0|0|0|0|0|0|0|0|0|0|0|0|0|0|0|0|0|0|0|0|0|0|0|0|0|0|0|0|0|0|0|0|0|0|0|0|0|0|0|0|0|0|0|0|0|0|0|0|0|0|0|0|0|0|0|0|0|0|0|0|0|0|0|0|0|0|0|0|0|0|0|0|0|0|0|0|0|0|0|0|0|0|0|0|0|0|0|0|0|0|0|0|0|0|0|0|697487</HistCounts>
      </HistItem>
    </Histograms>
    <Metadata>
      <MDI key="SourceBandIndex">2</MDI>
      <MDI key="STATISTICS_COUNT">30005000.000000</MDI>
      <MDI key="STATISTICS_COVARIANCES">1148.437457183666,677.2963791878365,169.398878761726,1476.414143520491</MDI>
      <MDI key="STATISTICS_EXCLUDEDVALUES"></MDI>
      <MDI key="STATISTICS_MAXIMUM">255</MDI>
      <MDI key="STATISTICS_MEAN">5.9276515580736</MDI>
      <MDI key="STATISTICS_MEDIAN">0.000000</MDI>
      <MDI key="STATISTICS_MINIMUM">0</MDI>
      <MDI key="STATISTICS_SKIPFACTORX">1</MDI>
      <MDI key="STATISTICS_SKIPFACTORY">1</MDI>
      <MDI key="STATISTICS_STDDEV">38.424134909201</MDI>
    </Metadata>
  </PAMRasterBand>
</PAMDataset>
